README.rst
setup.py
snmposter/__init__.py
snmposter/scripts.py
snmposter/snmposter.py
snmposter.egg-info/PKG-INFO
snmposter.egg-info/SOURCES.txt
snmposter.egg-info/dependency_links.txt
snmposter.egg-info/entry_points.txt
snmposter.egg-info/not-zip-safe
snmposter.egg-info/requires.txt
snmposter.egg-info/test_info.txt
snmposter.egg-info/top_level.txt